mb8611/__init__.py
mb8611/__main__.py
mb8611/api/__init__.py
mb8611/api/get_multiple_hnaps.py
mb8611/api/login.py
mb8611/api/settings.py
mb8611/api/types.py
mb8611/client.py
mb8611/constants.py
mb8611/main.py
mb8611/py.typed
mb8611/utils.py
mb8611-0.0.2.dist-info/LICENSE.txt
mb8611-0.0.2.dist-info/METADATA
mb8611-0.0.2.dist-info/WHEEL
mb8611-0.0.2.dist-info/entry_points.txt
mb8611-0.0.2.dist-info/RECORD
