Metadata-Version: 2.3
Name: mb8611
Version: 0.0.2
Summary: CLI tool for managing the Motorola MB8611 series modem and maybe other Motorola devices.
License: MIT
Keywords: command line
Author: Andrew Udvare
Author-email: audvare@gmail.com
Requires-Python: >=3.10,<3.14
Classifier: Development Status :: 2 - Pre-Alpha
Classifier: Intended Audience :: Developers
Classifier: License :: OSI Approved :: MIT License
Classifier: Programming Language :: Python
Classifier: Programming Language :: Python :: 3.10
Classifier: Programming Language :: Python :: 3.11
Classifier: Programming Language :: Python :: 3.12
Classifier: Programming Language :: Python :: 3.13
Classifier: Typing :: Typed
Classifier: Development Status :: 4 - Beta
Provides-Extra: erdantic
Requires-Dist: click (>=8.1.8,<9.0.0)
Requires-Dist: erdantic (<2.0) ; extra == "erdantic"
Requires-Dist: requests (>=2.32.3,<3.0.0)
Requires-Dist: typing-extensions (>=4.13.1,<5.0.0)
Project-URL: Documentation, https://mb8611.readthedocs.org
Project-URL: Homepage, https://tatsh.github.io/mb8611/
Project-URL: Issues, https://github.com/Tatsh/mb8611/issues
Project-URL: Repository, https://github.com/Tatsh/mb8611
